{
    "action": "create",
    "actor": {
        "email": "org-0058@herokumanager.com",
        "id": "f948a684-4345-4bd2-b6cd-85d4175b93a5"
    },
    "created_at": "2016-10-26T22:49:22Z",
    "id": "42963fb1-f4c6-4b3a-8b67-70f6db590ab4",
    "data": {
        "app": {
            "id": "7c454377-91c6-44e3-87a2-ecb16437ced9",
            "name": "polar-wildwood-81034"
        },
        "cname": null,
        "created_at": "2016-10-26T22:49:22Z",
        "hostname": "polar-wildwood-81034.herokuapp.com",
        "id": "e0470d2f-0f20-4280-ac85-a59e6cc5321d",
        "kind": "heroku",
        "status": "none",
        "updated_at": "2016-10-26T22:49:22Z"
    },
    "previous_data": {},
    "published_at": null,
    "resource": "domain",
    "sequence": null,
    "updated_at": "2016-10-26T22:49:22Z",
    "version": "application/vnd.heroku+json; version=3",
    "webhook_metadata": {
        "attempt": {
            "id": "8a44f820-2354-489d-9a11-a793cbf49979"
        },
        "delivery": {
            "id": "d244009a-670f-4340-88e9-789a4f9002d5"
        },
        "event": {
            "id": "42963fb1-f4c6-4b3a-8b67-70f6db590ab4",
            "include": "api:domain"
        },
        "webhook": {
            "id": "b54e6a7e-d162-4bd7-ab42-1011582c19cc"
        }
    }
}
